aktgestor_airflow_helpers/__init__.py
aktgestor_airflow_helpers-0.0.22.dist-info/METADATA
aktgestor_airflow_helpers-0.0.22.dist-info/WHEEL
aktgestor_airflow_helpers-0.0.22.dist-info/top_level.txt
aktgestor_airflow_helpers-0.0.22.dist-info/RECORD
