Metadata-Version: 2.1
Name: aktgestor-airflow-helpers
Version: 0.0.22
Summary: Helper functions for ariflow.
Home-page: UNKNOWN
Author: AktSoftware
Author-email: <francis@aktsoftware.com.br>
License: UNKNOWN
Platform: UNKNOWN
Classifier: Development Status :: 1 - Planning
Classifier: Intended Audience :: Developers
Classifier: Programming Language :: Python :: 3
Classifier: Operating System :: Unix
Classifier: Operating System :: MacOS :: MacOS X
Classifier: Operating System :: Microsoft :: Windows
Requires-Dist: jinjasql
Requires-Dist: pandas
